{
  "requestsFinished": 1,
  "requestsFailed": 0,
  "requestsRetries": 0,
  "requestsFailedPerMinute": 0,
  "requestsFinishedPerMinute": 2,
  "requestMinDurationMillis": 24006,
  "requestMaxDurationMillis": 24006,
  "requestTotalFailedDurationMillis": 0,
  "requestTotalFinishedDurationMillis": 24006,
  "crawlerStartedAt": "2025-11-08T11:45:54.606Z",
  "crawlerFinishedAt": "2025-11-08T11:46:19.096Z",
  "statsPersistedAt": "2025-11-08T11:46:19.096Z",
  "crawlerRuntimeMillis": 24846,
  "crawlerLastStartTimestamp": 1762602354250,
  "requestRetryHistogram": [
    1
  ],
  "statsId": 3,
  "requestAvgFailedDurationMillis": null,
  "requestAvgFinishedDurationMillis": 24006,
  "requestTotalDurationMillis": 24006,
  "requestsTotal": 1,
  "requestsWithStatusCode": {
    "200": 1
  },
  "errors": {},
  "retryErrors": {}
}