{
  "description": "Candidate KOL usernames for discovery. Successfully added KOLs are automatically removed from this list.",
  "lastUpdated": "2025-11-19T17:39:29.079Z",
  "totalCandidates": 133,
  "candidatesByTier": {
    "tier1_100k_500k": [],
    "tier2_50k_100k": [
      "TraderMayne",
      "CryptoGodJohn",
      "ImBagsy",
      "CryptoPosedon",
      "BTC_Archive",
      "thedefiedge",
      "MacroScope17",
      "DefiIgnas",
      "DeFi_Dad",
      "sassal0x",
      "ChainLinkGod",
      "NansenAI",
      "DuneAnalytics",
      "CryptoMichNL"
    ],
    "tier3_10k_50k": [
      "MilesDeutscher",
      "LomahCrypto",
      "AdamScochran",
      "CryptoCred",
      "TheCryptoDog",
      "cryptoyieldinfo",
      "CryptoGainz1",
      "SmartContracter",
      "KoroushAK",
      "TheCryptoCactus",
      "AltcoinPsycho",
      "DoveyWan",
      "Defi_gazer",
      "AltcoinDailyio",
      "coinbureau"
    ],
    "tier4_additional_10k_100k": [
      "TheMoonCarl",
      "CryptoTea_",
      "CryptoRUs",
      "AltcoinBuzz",
      "Crypto_Bitlord"
    ],
    "tier5_major_influencers_500k_5m": [
      "VitalikButerin",
      "cz_binance",
      "naval",
      "balajis",
      "APompliano",
      "elonmusk",
      "SatoshiLite",
      "justinsuntron",
      "CoinDesk",
      "Cointelegraph",
      "BTC_Archive",
      "BitcoinMagazine",
      "Bloomberg_Crypto"
    ],
    "tier6_trading_analysis_100k_500k": [
      "PeterLBrandt",
      "RektCapital",
      "CryptoMichNL",
      "PostyXBT",
      "nebraskangooner",
      "ToneVays",
      "CarpeNoctom",
      "ColdBloodShill",
      "CryptoKaiju",
      "Crypto_Chase",
      "CryptoGodJohn",
      "TraderXO",
      "Leonidasnft",
      "TraderMayne"
    ],
    "tier7_defi_protocols_50k_200k": [
      "AndreCronjeTech",
      "SBF_Alameda",
      "haydenzadams",
      "stanikulechov",
      "justinbons",
      "dcfgod",
      "ErikVoorhees",
      "VladZamfir",
      "RyanSAdams",
      "TrustlessState",
      "ljxie",
      "antiprosynth",
      "takenstheorem",
      "santiagoroel",
      "MessariCrypto"
    ],
    "tier8_nft_web3_50k_300k": [
      "gmoney",
      "punk6529",
      "GaryVee",
      "seedphrase",
      "punk4156",
      "pranksy",
      "farokh",
      "beaniemaxi",
      "franklinisbored",
      "j1mmyeth",
      "ArtOnBlockchain",
      "NFTherder",
      "punk9059",
      "GrailersDAO",
      "DCLBlogger"
    ],
    "tier9_layer1_layer2_30k_150k": [
      "StarkWareLtd",
      "Polkadot",
      "cosmos",
      "solana",
      "avalancheavax",
      "ethereum",
      "arbitrum",
      "Optimism",
      "0xPolygon",
      "zksync",
      "FantomFDN",
      "flow_blockchain",
      "Algorand",
      "Cardano",
      "NEARProtocol"
    ],
    "tier10_content_creators_20k_100k": [
      "IvanOnTech",
      "AltcoinDaily",
      "BenjaminCowen",
      "ByteSizeCapital",
      "CryptoCred",
      "CryptoZombie",
      "TheBlockchainPod",
      "Coin_Bureau",
      "TheMoon",
      "CryptoLark",
      "DataDash",
      "BoxMining"
    ],
    "tier11_researchers_10k_50k": [
      "haseebq",
      "nic__carter",
      "CaitlinLong_",
      "AutismCapital",
      "EminGunSirer",
      "laurashin",
      "twobitidiot",
      "CremeDeLaCrypto",
      "ThinkingUSD",
      "scottmelker",
      "cryptomanran",
      "AriDavidPaul",
      "econoar",
      "lawmaster",
      "0xSisyphus"
    ]
  }
}